letterboxd_stats/__init__.py
letterboxd_stats/cli.py
letterboxd_stats/data.py
letterboxd_stats/main.py
letterboxd_stats/tmdb.py
letterboxd_stats/web_scraper.py
letterboxd_stats-0.2.18.dist-info/LICENCE
letterboxd_stats-0.2.18.dist-info/METADATA
letterboxd_stats-0.2.18.dist-info/WHEEL
letterboxd_stats-0.2.18.dist-info/entry_points.txt
letterboxd_stats-0.2.18.dist-info/top_level.txt
letterboxd_stats-0.2.18.dist-info/RECORD
