Metadata-Version: 2.2
Name: letterboxd_stats
Version: 0.2.18
Summary: Get information about your Letterboxd activity.
Author: mBaratta96
Project-URL: Homepage, https://github.com/mBaratta96/letterboxd_stats
Project-URL: Bug Tracker, https://github.com/mBaratta96/letterboxd_stats/issues
Classifier: Programming Language :: Python :: 3
Classifier: License :: OSI Approved :: MIT License
Classifier: Operating System :: OS Independent
Requires-Python: >=3.8
License-File: LICENCE
Requires-Dist: ascii_magic~=2.3.0
Requires-Dist: inquirerpy~=0.3.4
Requires-Dist: lxml~=4.9.0
Requires-Dist: pandas~=2.2.1
Requires-Dist: pandarallel~=1.6.5
Requires-Dist: platformdirs~=3.0.0
Requires-Dist: requests~=2.31.0
Requires-Dist: rich~=13.3.5
Requires-Dist: tmdbv3api~=1.7.7
Requires-Dist: tomli~=2.0.1
Requires-Dist: tqdm~=4.65.0
